README.md
setup.cfg
setup.py
pyexecutors/__init__.py
pyexecutors.egg-info/PKG-INFO
pyexecutors.egg-info/SOURCES.txt
pyexecutors.egg-info/dependency_links.txt
pyexecutors.egg-info/top_level.txt
pyexecutors/executors/Executors.py
pyexecutors/executors/__init__.py
pyexecutors/holders/Tasks.py
pyexecutors/holders/__init__.py
pyexecutors/utils/BarrierHolder.py
pyexecutors/utils/thread_utils.py